{
  "version": "0.4.8",
  "generator": "piecemaker",
  "piece_cut_variant": "interlockingnubs",
  "full_size": 100,
  "sizes": [
    100
  ],
  "sides": [
    0
  ],
  "piece_count": 117,
  "image_author": "",
  "image_link": "",
  "image_title": "",
  "image_description": "",
  "image_width": 5472,
  "image_height": 3648,
  "outline_bbox": [
    4104,
    2736,
    9576,
    6384
  ],
  "puzzle_author": "",
  "puzzle_link": "",
  "table_width": 13680,
  "table_height": 9120,
  "piece_properties": [
    {
      "id": "0",
      "x": 1971,
      "y": 5262,
      "ox": 6911,
      "oy": 5164,
      "r": 0,
      "s": 0,
      "w": 572,
      "h": 417,
      "rotate": 0,
      "g": 0
    },
    {
      "id": "1",
      "x": 4254,
      "y": 8484,
      "ox": 7042,
      "oy": 3440,
      "r": 0,
      "s": 0,
      "w": 558,
      "h": 627,
      "rotate": 0,
      "g": 0
    },
    {
      "id": "2",
      "x": 3313,
      "y": 4952,
      "ox": 4104,
      "oy": 4225,
      "r": 0,
      "s": 0,
      "w": 551,
      "h": 641,
      "rotate": 0,
      "g": 0
    },
    {
      "id": "3",
      "x": 1711,
      "y": 1881,
      "ox": 6101,
      "oy": 3009,
      "r": 0,
      "s": 0,
      "w": 565,
      "h": 668,
      "rotate": 0,
      "g": 0
    },
    {
      "id": "4",
      "x": 2041,
      "y": 8399,
      "ox": 5347,
      "oy": 2736,
      "r": 0,
      "s": 0,
      "w": 453,
      "h": 514,
      "rotate": 0,
      "g": 0
    },
    {
      "id": "5",
      "x": 5803,
      "y": 99,
      "ox": 4904,
      "oy": 4641,
      "r": 0,
      "s": 0,
      "w": 481,
      "h": 536,
      "rotate": 0,
      "g": 0
    },
    {
      "id": "6",
      "x": 6403,
      "y": 1951,
      "ox": 5348,
      "oy": 4229,
      "r": 0,
      "s": 0,
      "w": 552,
      "h": 536,
      "rotate": 0,
      "g": 0
    },
    {
      "id": "7",
      "x": 1514,
      "y": 161,
      "ox": 5682,
      "oy": 5153,
      "r": 0,
      "s": 0,
      "w": 635,
      "h": 425,
      "rotate": 0,
      "g": 0
    },
    {
      "id": "8",
      "x": 159,
      "y": 553,
      "ox": 6919,
      "oy": 5971,
      "r": 0,
      "s": 0,
      "w": 560,
      "h": 412,
      "rotate": 0,
      "g": 0
    },
    {
      "id": "9",
      "x": 3128,
      "y": 3523,
      "ox": 7880,
      "oy": 5461,
      "r": 0,
      "s": 0,
      "w": 437,
      "h": 627,
      "rotate": 0,
      "g": 0
    },
    {
      "id": "10",
      "x": 1723,
      "y": 5995,
      "ox": 6923,
      "oy": 4634,
      "r": 0,
      "s": 0,
      "w": 683,
      "h": 656,
      "rotate": 0,
      "g": 0
    },
    {
      "id": "11",
      "x": 1139,
      "y": 7839,
      "ox": 6079,
      "oy": 3546,
      "r": 0,
      "s": 0,
      "w": 652,
      "h": 513,
      "rotate": 0,
      "g": 0
    },
    {
      "id": "12",
      "x": 9517,
      "y": 331,
      "ox": 4942,
      "oy": 3527,
      "r": 0,
      "s": 0,
      "w": 560,
      "h": 427,
      "rotate": 0,
      "g": 0
    },
    {
      "id": "13",
      "x": 7072,
      "y": 684,
      "ox": 6627,
      "oy": 3844,
      "r": 0,
      "s": 0,
      "w": 444,
      "h": 645,
      "rotate": 0,
      "g": 0
    },
    {
      "id": "14",
      "x": 668,
      "y": 4253,
      "ox": 6200,
      "oy": 2736,
      "r": 0,
      "s": 0,
      "w": 568,
      "h": 441,
      "rotate": 0,
      "g": 0
    },
    {
      "id": "15",
      "x": 4752,
      "y": 7900,
      "ox": 9152,
      "oy": 5562,
      "r": 0,
      "s": 0,
      "w": 424,
      "h": 424,
      "rotate": 0,
      "g": 0
    },
    {
      "id": "16",
      "x": 9055,
      "y": 8318,
      "ox": 6625,
      "oy": 5451,
      "r": 0,
      "s": 0,
      "w": 428,
      "h": 566,
      "rotate": 0,
      "g": 0
    },
    {
      "id": "17",
      "x": 2521,
      "y": 1865,
      "ox": 5786,
      "oy": 4645,
      "r": 0,
      "s": 0,
      "w": 550,
      "h": 661,
      "rotate": 0,
      "g": 0
    },
    {
      "id": "18",
      "x": 4518,
      "y": 6486,
      "ox": 8733,
      "oy": 4235,
      "r": 0,
      "s": 0,
      "w": 456,
      "h": 534,
      "rotate": 0,
      "g": 0
    },
    {
      "id": "19",
      "x": 2433,
      "y": 3758,
      "ox": 5771,
      "oy": 3016,
      "r": 0,
      "s": 0,
      "w": 443,
      "h": 566,
      "rotate": 0,
      "g": 0
    },
    {
      "id": "20",
      "x": 9169,
      "y": 795,
      "ox": 4495,
      "oy": 3022,
      "r": 0,
      "s": 0,
      "w": 483,
      "h": 634,
      "rotate": 0,
      "g": 0
    },
    {
      "id": "21",
      "x": 1578,
      "y": 7320,
      "ox": 6946,
      "oy": 3949,
      "r": 0,
      "s": 0,
      "w": 532,
      "h": 443,
      "rotate": 0,
      "g": 0
    },
    {
      "id": "22",
      "x": 3698,
      "y": 343,
      "ox": 7469,
      "oy": 2736,
      "r": 0,
      "s": 0,
      "w": 562,
      "h": 525,
      "rotate": 0,
      "g": 0
    },
    {
      "id": "23",
      "x": 6098,
      "y": 908,
      "ox": 4392,
      "oy": 5166,
      "r": 0,
      "s": 0,
      "w": 666,
      "h": 538,
      "rotate": 0,
      "g": 0
    },
    {
      "id": "24",
      "x": 5362,
      "y": 1873,
      "ox": 4104,
      "oy": 2736,
      "r": 0,
      "s": 0,
      "w": 524,
      "h": 425,
      "rotate": 0,
      "g": 0
    },
    {
      "id": "25",
      "x": 7580,
      "y": 2078,
      "ox": 7044,
      "oy": 2736,
      "r": 0,
      "s": 0,
      "w": 552,
      "h": 532,
      "rotate": 0,
      "g": 0
    },
    {
      "id": "26",
      "x": 7925,
      "y": 8254,
      "ox": 6184,
      "oy": 5440,
      "r": 0,
      "s": 0,
      "w": 582,
      "h": 552,
      "rotate": 0,
      "g": 0
    },
    {
      "id": "27",
      "x": 1580,
      "y": 1078,
      "ox": 6628,
      "oy": 2736,
      "r": 0,
      "s": 0,
      "w": 540,
      "h": 437,
      "rotate": 0,
      "g": 0
    },
    {
      "id": "28",
      "x": 8471,
      "y": 1006,
      "ox": 5355,
      "oy": 5155,
      "r": 0,
      "s": 0,
      "w": 438,
      "h": 540,
      "rotate": 0,
      "g": 0
    },
    {
      "id": "29",
      "x": 896,
      "y": 3091,
      "ox": 8711,
      "oy": 3443,
      "r": 0,
      "s": 0,
      "w": 448,
      "h": 540,
      "rotate": 0,
      "g": 0
    },
    {
      "id": "30",
      "x": 7569,
      "y": 7499,
      "ox": 8305,
      "oy": 3545,
      "r": 0,
      "s": 0,
      "w": 559,
      "h": 413,
      "rotate": 0,
      "g": 0
    },
    {
      "id": "31",
      "x": 1109,
      "y": 1614,
      "ox": 7047,
      "oy": 4236,
      "r": 0,
      "s": 0,
      "w": 430,
      "h": 529,
      "rotate": 0,
      "g": 0
    },
    {
      "id": "32",
      "x": 2988,
      "y": 853,
      "ox": 4945,
      "oy": 5569,
      "r": 0,
      "s": 0,
      "w": 429,
      "h": 527,
      "rotate": 0,
      "g": 0
    },
    {
      "id": "33",
      "x": 441,
      "y": 5536,
      "ox": 8726,
      "oy": 5538,
      "r": 0,
      "s": 0,
      "w": 532,
      "h": 576,
      "rotate": 0,
      "g": 0
    },
    {
      "id": "34",
      "x": 377,
      "y": 6830,
      "ox": 7873,
      "oy": 3947,
      "r": 0,
      "s": 0,
      "w": 450,
      "h": 540,
      "rotate": 0,
      "g": 0
    },
    {
      "id": "35",
      "x": 3205,
      "y": 2027,
      "ox": 5779,
      "oy": 3433,
      "r": 0,
      "s": 0,
      "w": 450,
      "h": 525,
      "rotate": 0,
      "g": 0
    },
    {
      "id": "36",
      "x": 172,
      "y": 8335,
      "ox": 7468,
      "oy": 4726,
      "r": 0,
      "s": 0,
      "w": 458,
      "h": 573,
      "rotate": 0,
      "g": 0
    },
    {
      "id": "37",
      "x": 3525,
      "y": 7212,
      "ox": 5360,
      "oy": 3117,
      "r": 0,
      "s": 0,
      "w": 537,
      "h": 561,
      "rotate": 0,
      "g": 0
    },
    {
      "id": "38",
      "x": 1337,
      "y": 3999,
      "ox": 9014,
      "oy": 3829,
      "r": 0,
      "s": 0,
      "w": 562,
      "h": 657,
      "rotate": 0,
      "g": 0
    },
    {
      "id": "39",
      "x": 9313,
      "y": 1804,
      "ox": 6508,
      "oy": 4657,
      "r": 0,
      "s": 0,
      "w": 546,
      "h": 527,
      "rotate": 0,
      "g": 0
    },
    {
      "id": "40",
      "x": 949,
      "y": 6292,
      "ox": 4419,
      "oy": 3511,
      "r": 0,
      "s": 0,
      "w": 649,
      "h": 444,
      "rotate": 0,
      "g": 0
    },
    {
      "id": "41",
      "x": 5699,
      "y": 7940,
      "ox": 4104,
      "oy": 4759,
      "r": 0,
      "s": 0,
      "w": 526,
      "h": 544,
      "rotate": 0,
      "g": 0
    },
    {
      "id": "42",
      "x": 440,
      "y": 4881,
      "ox": 4827,
      "oy": 2736,
      "r": 0,
      "s": 0,
      "w": 667,
      "h": 408,
      "rotate": 0,
      "g": 0
    },
    {
      "id": "43",
      "x": 1047,
      "y": 227,
      "ox": 8312,
      "oy": 3010,
      "r": 0,
      "s": 0,
      "w": 425,
      "h": 639,
      "rotate": 0,
      "g": 0
    },
    {
      "id": "44",
      "x": 6840,
      "y": 6791,
      "ox": 4104,
      "oy": 3032,
      "r": 0,
      "s": 0,
      "w": 532,
      "h": 530,
      "rotate": 0,
      "g": 0
    },
    {
      "id": "45",
      "x": 2307,
      "y": 1089,
      "ox": 4382,
      "oy": 5850,
      "r": 0,
      "s": 0,
      "w": 671,
      "h": 533,
      "rotate": 0,
      "g": 0
    },
    {
      "id": "46",
      "x": 1803,
      "y": 3135,
      "ox": 5363,
      "oy": 3537,
      "r": 0,
      "s": 0,
      "w": 532,
      "h": 525,
      "rotate": 0,
      "g": 0
    },
    {
      "id": "47",
      "x": 4449,
      "y": 1636,
      "ox": 6939,
      "oy": 3138,
      "r": 0,
      "s": 0,
      "w": 675,
      "h": 420,
      "rotate": 0,
      "g": 0
    },
    {
      "id": "48",
      "x": 4320,
      "y": 427,
      "ox": 6181,
      "oy": 4224,
      "r": 0,
      "s": 0,
      "w": 571,
      "h": 545,
      "rotate": 0,
      "g": 0
    },
    {
      "id": "49",
      "x": 361,
      "y": 7446,
      "ox": 5338,
      "oy": 3948,
      "r": 0,
      "s": 0,
      "w": 451,
      "h": 444,
      "rotate": 0,
      "g": 0
    },
    {
      "id": "50",
      "x": 819,
      "y": 2404,
      "ox": 4493,
      "oy": 4344,
      "r": 0,
      "s": 0,
      "w": 493,
      "h": 530,
      "rotate": 0,
      "g": 0
    },
    {
      "id": "51",
      "x": 8701,
      "y": 6463,
      "ox": 6627,
      "oy": 3448,
      "r": 0,
      "s": 0,
      "w": 525,
      "h": 512,
      "rotate": 0,
      "g": 0
    },
    {
      "id": "52",
      "x": 6703,
      "y": 7379,
      "ox": 7468,
      "oy": 3416,
      "r": 0,
      "s": 0,
      "w": 556,
      "h": 664,
      "rotate": 0,
      "g": 0
    },
    {
      "id": "53",
      "x": 4651,
      "y": 1082,
      "ox": 9035,
      "oy": 4630,
      "r": 0,
      "s": 0,
      "w": 541,
      "h": 543,
      "rotate": 0,
      "g": 0
    },
    {
      "id": "54",
      "x": 7793,
      "y": 6692,
      "ox": 7368,
      "oy": 3951,
      "r": 0,
      "s": 0,
      "w": 661,
      "h": 408,
      "rotate": 0,
      "g": 0
    },
    {
      "id": "55",
      "x": 8422,
      "y": 116,
      "ox": 7889,
      "oy": 3545,
      "r": 0,
      "s": 0,
      "w": 528,
      "h": 517,
      "rotate": 0,
      "g": 0
    },
    {
      "id": "56",
      "x": 8471,
      "y": 7026,
      "ox": 4499,
      "oy": 3833,
      "r": 0,
      "s": 0,
      "w": 551,
      "h": 635,
      "rotate": 0,
      "g": 0
    },
    {
      "id": "57",
      "x": 4932,
      "y": 97,
      "ox": 7778,
      "oy": 4657,
      "r": 0,
      "s": 0,
      "w": 544,
      "h": 537,
      "rotate": 0,
      "g": 0
    },
    {
      "id": "58",
      "x": 8472,
      "y": 1551,
      "ox": 5262,
      "oy": 5572,
      "r": 0,
      "s": 0,
      "w": 651,
      "h": 409,
      "rotate": 0,
      "g": 0
    },
    {
      "id": "59",
      "x": 3155,
      "y": 4309,
      "ox": 4104,
      "oy": 5131,
      "r": 0,
      "s": 0,
      "w": 423,
      "h": 560,
      "rotate": 0,
      "g": 0
    },
    {
      "id": "60",
      "x": 1937,
      "y": 6749,
      "ox": 8208,
      "oy": 2736,
      "r": 0,
      "s": 0,
      "w": 637,
      "h": 414,
      "rotate": 0,
      "g": 0
    },
    {
      "id": "61",
      "x": 3695,
      "y": 1680,
      "ox": 5237,
      "oy": 4645,
      "r": 0,
      "s": 0,
      "w": 677,
      "h": 656,
      "rotate": 0,
      "g": 0
    },
    {
      "id": "62",
      "x": 2865,
      "y": 2954,
      "ox": 9046,
      "oy": 3445,
      "r": 0,
      "s": 0,
      "w": 530,
      "h": 544,
      "rotate": 0,
      "g": 0
    },
    {
      "id": "63",
      "x": 5602,
      "y": 7080,
      "ox": 4104,
      "oy": 3443,
      "r": 0,
      "s": 0,
      "w": 423,
      "h": 608,
      "rotate": 0,
      "g": 0
    },
    {
      "id": "64",
      "x": 7606,
      "y": 151,
      "ox": 6912,
      "oy": 5450,
      "r": 0,
      "s": 0,
      "w": 671,
      "h": 629,
      "rotate": 0,
      "g": 0
    },
    {
      "id": "65",
      "x": 3091,
      "y": 5804,
      "ox": 5660,
      "oy": 3825,
      "r": 0,
      "s": 0,
      "w": 687,
      "h": 543,
      "rotate": 0,
      "g": 0
    },
    {
      "id": "66",
      "x": 246,
      "y": 1382,
      "ox": 6178,
      "oy": 5139,
      "r": 0,
      "s": 0,
      "w": 453,
      "h": 438,
      "rotate": 0,
      "g": 0
    },
    {
      "id": "67",
      "x": 644,
      "y": 3664,
      "ox": 7470,
      "oy": 5566,
      "r": 0,
      "s": 0,
      "w": 526,
      "h": 547,
      "rotate": 0,
      "g": 0
    },
    {
      "id": "68",
      "x": 2921,
      "y": 7124,
      "ox": 4490,
      "oy": 5568,
      "r": 0,
      "s": 0,
      "w": 576,
      "h": 423,
      "rotate": 0,
      "g": 0
    },
    {
      "id": "69",
      "x": 5998,
      "y": 8570,
      "ox": 6077,
      "oy": 5849,
      "r": 0,
      "s": 0,
      "w": 687,
      "h": 534,
      "rotate": 0,
      "g": 0
    },
    {
      "id": "70",
      "x": 4281,
      "y": 7923,
      "ox": 9152,
      "oy": 3103,
      "r": 0,
      "s": 0,
      "w": 424,
      "h": 449,
      "rotate": 0,
      "g": 0
    },
    {
      "id": "71",
      "x": 5179,
      "y": 6506,
      "ox": 7333,
      "oy": 5974,
      "r": 0,
      "s": 0,
      "w": 600,
      "h": 409,
      "rotate": 0,
      "g": 0
    },
    {
      "id": "72",
      "x": 2624,
      "y": 478,
      "ox": 7784,
      "oy": 3004,
      "r": 0,
      "s": 0,
      "w": 658,
      "h": 641,
      "rotate": 0,
      "g": 0
    },
    {
      "id": "73",
      "x": 7708,
      "y": 842,
      "ox": 8712,
      "oy": 2736,
      "r": 0,
      "s": 0,
      "w": 445,
      "h": 541,
      "rotate": 0,
      "g": 0
    },
    {
      "id": "74",
      "x": 3104,
      "y": 7107,
      "ox": 4844,
      "oy": 3031,
      "r": 0,
      "s": 0,
      "w": 631,
      "h": 627,
      "rotate": 0,
      "g": 0
    },
    {
      "id": "75",
      "x": 4796,
      "y": 2130,
      "ox": 8711,
      "oy": 3835,
      "r": 0,
      "s": 0,
      "w": 445,
      "h": 531,
      "rotate": 0,
      "g": 0
    },
    {
      "id": "76",
      "x": 6103,
      "y": 6641,
      "ox": 6205,
      "oy": 4640,
      "r": 0,
      "s": 0,
      "w": 431,
      "h": 649,
      "rotate": 0,
      "g": 0
    },
    {
      "id": "77",
      "x": 6297,
      "y": 8134,
      "ox": 4104,
      "oy": 3951,
      "r": 0,
      "s": 0,
      "w": 563,
      "h": 409,
      "rotate": 0,
      "g": 0
    },
    {
      "id": "78",
      "x": 2917,
      "y": 8521,
      "ox": 8310,
      "oy": 4228,
      "r": 0,
      "s": 0,
      "w": 531,
      "h": 541,
      "rotate": 0,
      "g": 0
    },
    {
      "id": "79",
      "x": 4746,
      "y": 7327,
      "ox": 6619,
      "oy": 5845,
      "r": 0,
      "s": 0,
      "w": 434,
      "h": 538,
      "rotate": 0,
      "g": 0
    },
    {
      "id": "80",
      "x": 3574,
      "y": 8455,
      "ox": 4524,
      "oy": 2736,
      "r": 0,
      "s": 0,
      "w": 452,
      "h": 408,
      "rotate": 0,
      "g": 0
    },
    {
      "id": "81",
      "x": 7388,
      "y": 8314,
      "ox": 4936,
      "oy": 5978,
      "r": 0,
      "s": 0,
      "w": 435,
      "h": 405,
      "rotate": 0,
      "g": 0
    },
    {
      "id": "82",
      "x": 2922,
      "y": 358,
      "ox": 4920,
      "oy": 5038,
      "r": 0,
      "s": 0,
      "w": 559,
      "h": 656,
      "rotate": 0,
      "g": 0
    },
    {
      "id": "83",
      "x": 6517,
      "y": 82,
      "ox": 7353,
      "oy": 5164,
      "r": 0,
      "s": 0,
      "w": 547,
      "h": 536,
      "rotate": 0,
      "g": 0
    },
    {
      "id": "84",
      "x": 7385,
      "y": 69,
      "ox": 9025,
      "oy": 2736,
      "r": 0,
      "s": 0,
      "w": 550,
      "h": 542,
      "rotate": 0,
      "g": 0
    },
    {
      "id": "85",
      "x": 3293,
      "y": 1351,
      "ox": 8727,
      "oy": 4645,
      "r": 0,
      "s": 0,
      "w": 439,
      "h": 528,
      "rotate": 0,
      "g": 0
    },
    {
      "id": "86",
      "x": 4773,
      "y": 1301,
      "ox": 6626,
      "oy": 4324,
      "r": 0,
      "s": 0,
      "w": 529,
      "h": 460,
      "rotate": 0,
      "g": 0
    },
    {
      "id": "87",
      "x": 2133,
      "y": 4579,
      "ox": 9032,
      "oy": 5852,
      "r": 0,
      "s": 0,
      "w": 544,
      "h": 532,
      "rotate": 0,
      "g": 0
    },
    {
      "id": "88",
      "x": 7356,
      "y": 1458,
      "ox": 5238,
      "oy": 5881,
      "r": 0,
      "s": 0,
      "w": 657,
      "h": 503,
      "rotate": 0,
      "g": 0
    },
    {
      "id": "89",
      "x": 3801,
      "y": 6484,
      "ox": 8591,
      "oy": 5039,
      "r": 0,
      "s": 0,
      "w": 680,
      "h": 634,
      "rotate": 0,
      "g": 0
    },
    {
      "id": "90",
      "x": 2192,
      "y": 7604,
      "ox": 9026,
      "oy": 4351,
      "r": 0,
      "s": 0,
      "w": 549,
      "h": 423,
      "rotate": 0,
      "g": 0
    },
    {
      "id": "91",
      "x": 6138,
      "y": 1502,
      "ox": 4104,
      "oy": 5977,
      "r": 0,
      "s": 0,
      "w": 424,
      "h": 406,
      "rotate": 0,
      "g": 0
    },
    {
      "id": "92",
      "x": 1171,
      "y": 5308,
      "ox": 8172,
      "oy": 5571,
      "r": 0,
      "s": 0,
      "w": 701,
      "h": 410,
      "rotate": 0,
      "g": 0
    },
    {
      "id": "93",
      "x": 2279,
      "y": 2886,
      "ox": 7777,
      "oy": 4356,
      "r": 0,
      "s": 0,
      "w": 667,
      "h": 409,
      "rotate": 0,
      "g": 0
    },
    {
      "id": "94",
      "x": 4565,
      "y": 6668,
      "ox": 5785,
      "oy": 5455,
      "r": 0,
      "s": 0,
      "w": 545,
      "h": 659,
      "rotate": 0,
      "g": 0
    },
    {
      "id": "95",
      "x": 3923,
      "y": 1102,
      "ox": 7772,
      "oy": 5949,
      "r": 0,
      "s": 0,
      "w": 544,
      "h": 434,
      "rotate": 0,
      "g": 0
    },
    {
      "id": "96",
      "x": 8784,
      "y": 7020,
      "ox": 7452,
      "oy": 3140,
      "r": 0,
      "s": 0,
      "w": 447,
      "h": 409,
      "rotate": 0,
      "g": 0
    },
    {
      "id": "97",
      "x": 292,
      "y": 3,
      "ox": 8204,
      "oy": 3830,
      "r": 0,
      "s": 0,
      "w": 662,
      "h": 548,
      "rotate": 0,
      "g": 0
    },
    {
      "id": "98",
      "x": 1165,
      "y": 1955,
      "ox": 6507,
      "oy": 5041,
      "r": 0,
      "s": 0,
      "w": 554,
      "h": 552,
      "rotate": 0,
      "g": 0
    },
    {
      "id": "99",
      "x": 193,
      "y": 203,
      "ox": 9152,
      "oy": 5045,
      "r": 0,
      "s": 0,
      "w": 424,
      "h": 656,
      "rotate": 0,
      "g": 0
    },
    {
      "id": "100",
      "x": 2409,
      "y": 5695,
      "ox": 7781,
      "oy": 5051,
      "r": 0,
      "s": 0,
      "w": 557,
      "h": 524,
      "rotate": 0,
      "g": 0
    },
    {
      "id": "101",
      "x": 256,
      "y": 2115,
      "ox": 7861,
      "oy": 2736,
      "r": 0,
      "s": 0,
      "w": 454,
      "h": 408,
      "rotate": 0,
      "g": 0
    },
    {
      "id": "102",
      "x": 946,
      "y": 1088,
      "ox": 6506,
      "oy": 3034,
      "r": 0,
      "s": 0,
      "w": 550,
      "h": 519,
      "rotate": 0,
      "g": 0
    },
    {
      "id": "103",
      "x": 1556,
      "y": 1363,
      "ox": 5780,
      "oy": 4244,
      "r": 0,
      "s": 0,
      "w": 546,
      "h": 523,
      "rotate": 0,
      "g": 0
    },
    {
      "id": "104",
      "x": 3323,
      "y": 6138,
      "ox": 8175,
      "oy": 5065,
      "r": 0,
      "s": 0,
      "w": 563,
      "h": 646,
      "rotate": 0,
      "g": 0
    },
    {
      "id": "105",
      "x": 3543,
      "y": 7866,
      "ox": 4104,
      "oy": 5571,
      "r": 0,
      "s": 0,
      "w": 523,
      "h": 516,
      "rotate": 0,
      "g": 0
    },
    {
      "id": "106",
      "x": 6631,
      "y": 1503,
      "ox": 4944,
      "oy": 3854,
      "r": 0,
      "s": 0,
      "w": 556,
      "h": 605,
      "rotate": 0,
      "g": 0
    },
    {
      "id": "107",
      "x": 2752,
      "y": 4539,
      "ox": 8596,
      "oy": 3130,
      "r": 0,
      "s": 0,
      "w": 677,
      "h": 456,
      "rotate": 0,
      "g": 0
    },
    {
      "id": "108",
      "x": 8330,
      "y": 7693,
      "ox": 6190,
      "oy": 3944,
      "r": 0,
      "s": 0,
      "w": 573,
      "h": 438,
      "rotate": 0,
      "g": 0
    },
    {
      "id": "109",
      "x": 1234,
      "y": 4723,
      "ox": 8195,
      "oy": 5870,
      "r": 0,
      "s": 0,
      "w": 542,
      "h": 513,
      "rotate": 0,
      "g": 0
    },
    {
      "id": "110",
      "x": 1648,
      "y": 5253,
      "ox": 8206,
      "oy": 4647,
      "r": 0,
      "s": 0,
      "w": 661,
      "h": 530,
      "rotate": 0,
      "g": 0
    },
    {
      "id": "111",
      "x": 1885,
      "y": 2657,
      "ox": 7339,
      "oy": 4223,
      "r": 0,
      "s": 0,
      "w": 557,
      "h": 644,
      "rotate": 0,
      "g": 0
    },
    {
      "id": "112",
      "x": 5414,
      "y": 6570,
      "ox": 5669,
      "oy": 2736,
      "r": 0,
      "s": 0,
      "w": 668,
      "h": 424,
      "rotate": 0,
      "g": 0
    },
    {
      "id": "113",
      "x": 2628,
      "y": 8201,
      "ox": 8610,
      "oy": 5945,
      "r": 0,
      "s": 0,
      "w": 575,
      "h": 438,
      "rotate": 0,
      "g": 0
    },
    {
      "id": "114",
      "x": 1370,
      "y": 1024,
      "ox": 4514,
      "oy": 4754,
      "r": 0,
      "s": 0,
      "w": 562,
      "h": 528,
      "rotate": 0,
      "g": 0
    },
    {
      "id": "115",
      "x": 834,
      "y": 8618,
      "ox": 4841,
      "oy": 4329,
      "r": 0,
      "s": 0,
      "w": 636,
      "h": 436,
      "rotate": 0,
      "g": 0
    },
    {
      "id": "116",
      "x": 1319,
      "y": 678,
      "ox": 5776,
      "oy": 5967,
      "r": 0,
      "s": 0,
      "w": 442,
      "h": 416,
      "rotate": 0,
      "g": 0
    }
  ]
}